odoo/addons/project_sequence/README.rst
odoo/addons/project_sequence/__init__.py
odoo/addons/project_sequence/__manifest__.py
odoo/addons/project_sequence/data/ir_sequence.xml
odoo/addons/project_sequence/i18n/es.po
odoo/addons/project_sequence/i18n/project_sequence.pot
odoo/addons/project_sequence/models/__init__.py
odoo/addons/project_sequence/models/project_project.py
odoo/addons/project_sequence/readme/CONFIGURE.rst
odoo/addons/project_sequence/readme/CONTRIBUTORS.rst
odoo/addons/project_sequence/readme/CREDITS.rst
odoo/addons/project_sequence/readme/DESCRIPTION.rst
odoo/addons/project_sequence/readme/USAGE.rst
odoo/addons/project_sequence/static/description/icon.png
odoo/addons/project_sequence/static/description/index.html
odoo/addons/project_sequence/tests/__init__.py
odoo/addons/project_sequence/tests/test_project_sequence.py
odoo/addons/project_sequence/views/project_project.xml
odoo/addons/project_sequence/wizards/__init__.py
odoo/addons/project_sequence/wizards/res_config_settings.py
odoo/addons/project_sequence/wizards/res_config_settings_view.xml
odoo14_addon_project_sequence-14.0.0.2.0.dist-info/METADATA
odoo14_addon_project_sequence-14.0.0.2.0.dist-info/WHEEL
odoo14_addon_project_sequence-14.0.0.2.0.dist-info/top_level.txt
odoo14_addon_project_sequence-14.0.0.2.0.dist-info/RECORD
